[ {
  "id" : 1,
  "usuario" : {
    "username" : "santi",
    "password" : "123",
    "tipoUsuario" : "CLIENTE"
  },
  "nombre" : "santi",
  "apellido" : "blanco",
  "dni" : "123",
  "domicilio" : "saturno 12",
  "telefono" : "123",
  "saldo" : 500.0,
  "estaActivo" : true
}, {
  "id" : 2,
  "usuario" : {
    "username" : "mhawke",
    "password" : "123",
    "tipoUsuario" : "CLIENTE"
  },
  "nombre" : "marian",
  "apellido" : "hawke",
  "dni" : "124",
  "domicilio" : "urano 12",
  "telefono" : "123",
  "saldo" : 500.0,
  "estaActivo" : true
}, {
  "id" : 0,
  "usuario" : {
    "username" : "jespinoza",
    "password" : "125",
    "tipoUsuario" : "CLIENTE"
  },
  "nombre" : "Jorge",
  "apellido" : "Espinoza",
  "dni" : "11111",
  "domicilio" : "Falsa123",
  "telefono" : "223",
  "saldo" : 0.0,
  "estaActivo" : false
} ]